yta_docker_ollama/__init__.py
yta_docker_ollama-0.0.3.dist-info/licenses/LICENSE
yta_docker_ollama-0.0.3.dist-info/METADATA
yta_docker_ollama-0.0.3.dist-info/WHEEL
yta_docker_ollama-0.0.3.dist-info/RECORD
