Metadata-Version: 2.4
Name: yta-docker-ollama
Version: 0.0.3
Summary: Youtube Autonomous Docker Ollama Module
License-File: LICENSE
Author: danialcala94
Author-email: danielalcalavalera@gmail.com
Requires-Python: ==3.9
Classifier: Programming Language :: Python :: 3
Classifier: Programming Language :: Python :: 3.9
Requires-Dist: yta_validation (>=0.0.1,<1.0.0)
